deeptools/SES_scaleFactor.py
deeptools/__init__.py
deeptools/alignmentSieve.py
deeptools/bamCompare.py
deeptools/bamCoverage.py
deeptools/bamHandler.py
deeptools/bamPEFragmentSize.py
deeptools/bigwigAverage.py
deeptools/bigwigCompare.py
deeptools/cm.py
deeptools/computeGCBias.py
deeptools/computeMatrix.py
deeptools/computeMatrixOperations.py
deeptools/correctGCBias.py
deeptools/correlation.py
deeptools/correlation_heatmap.py
deeptools/countReadsPerBin.py
deeptools/deeptools_list_tools.py
deeptools/estimateReadFiltering.py
deeptools/estimateScaleFactor.py
deeptools/getFragmentAndReadSize.py
deeptools/getRatio.py
deeptools/getScaleFactor.py
deeptools/getScorePerBigWigBin.py
deeptools/heatmapper.py
deeptools/heatmapper_utilities.py
deeptools/mapReduce.py
deeptools/misc.py
deeptools/multiBamSummary.py
deeptools/multiBigwigSummary.py
deeptools/parserCommon.py
deeptools/plotCorrelation.py
deeptools/plotCoverage.py
deeptools/plotEnrichment.py
deeptools/plotFingerprint.py
deeptools/plotHeatmap.py
deeptools/plotPCA.py
deeptools/plotProfile.py
deeptools/sumCoveragePerBin.py
deeptools/utilities.py
deeptools/writeBedGraph.py
deeptools/writeBedGraph_bam_and_bw.py
deepTools-3.5.6.dist-info/LICENSE.txt
deepTools-3.5.6.dist-info/METADATA
deepTools-3.5.6.dist-info/WHEEL
deepTools-3.5.6.dist-info/entry_points.txt
deepTools-3.5.6.dist-info/top_level.txt
deepTools-3.5.6.dist-info/RECORD
