Metadata-Version: 2.2
Name: deepTools
Version: 3.5.6
Summary: Useful tools for exploring deep sequencing data.
Author: Fidel Ramirez, Devon P Ryan, Björn Grüning, Friederike Dündar, Sarah Diehl, Vivek Bhardwaj, Fabian Kilpert, Andreas S Richter, Steffen Heyne, Thomas Manke
Author-email: bioinfo-core@ie-freiburg.mpg.de
License: The file deeptools/cm.py is licensed under the BSD license, see a copy in that file. The remainder of the code is licensed under the MIT license:
Project-URL: homepage, https://pypi.python.org/pypi/deepTools/
Project-URL: documentation, https://deeptools.readthedocs.io/en/latest/
Project-URL: repository, https://github.com/deeptools/deepTools
Classifier: Intended Audience :: Science/Research
Classifier: Topic :: Scientific/Engineering :: Bio-Informatics
Requires-Python: >3.8
License-File: LICENSE.txt
Requires-Dist: numpy>=2.0.0
Requires-Dist: scipy>=0.17.0
Requires-Dist: matplotlib>=3.5.0
Requires-Dist: pysam>=0.14.0
Requires-Dist: numpydoc>=0.5
Requires-Dist: pyBigWig>=0.2.1
Requires-Dist: py2bit>=0.2.0
Requires-Dist: plotly>=4.9
Requires-Dist: deeptoolsintervals>=0.1.8
Provides-Extra: actions
Requires-Dist: flake8; extra == "actions"
Requires-Dist: pytest; extra == "actions"
Requires-Dist: twine; extra == "actions"
Requires-Dist: build; extra == "actions"
Requires-Dist: planemo; extra == "actions"
